geo_utils/__init__.py
geo_utils/__main__.py
geo_utils/utils.py
geo_data_utils-1.1.1.dist-info/LICENSE.txt
geo_data_utils-1.1.1.dist-info/METADATA
geo_data_utils-1.1.1.dist-info/WHEEL
geo_data_utils-1.1.1.dist-info/entry_points.txt
geo_data_utils-1.1.1.dist-info/top_level.txt
geo_data_utils-1.1.1.dist-info/RECORD
