Metadata-Version: 2.1
Name: geo-data-utils
Version: 1.1.1
Summary: Geology Data Utils
Home-page: https://gitlab.com/csiro-geoanalytics/python-shared/geo-data-utils
Maintainer: Samuel Bradley
Maintainer-email: sam.bradley@csiro.au
License: MIT
Platform: UNKNOWN
Classifier: Development Status :: 4 - Beta
Classifier: Intended Audience :: Science/Research
Classifier: License :: OSI Approved :: MIT License
Classifier: Programming Language :: Python :: 3
Classifier: Programming Language :: Python :: 3.6
Classifier: Programming Language :: Python :: 3.7
Classifier: Programming Language :: Python :: 3.8
Requires-Python: >=3.5, <4
License-File: LICENSE.txt
Requires-Dist: pandas
Requires-Dist: loguru
Requires-Dist: click
Requires-Dist: xlrd
Requires-Dist: openpyxl
Requires-Dist: pyyaml
Requires-Dist: numpy
Requires-Dist: plotly
Requires-Dist: colorcet
